rBat/__init__.py
rBat/SummaryMeasures/CommanderSM.py
rBat/SummaryMeasures/DependenciesSM.py
rBat/SummaryMeasures/FieldSM.py
rBat/SummaryMeasures/FunctionalSM.py
rBat/SummaryMeasures/__init__.py
rBat/preprocessing/Preprocessor.py
rBat/preprocessing/__init__.py
rBat/preprocessing/segmentation.py
rBat/preprocessing/smoothing.py
rBat/preprocessing/testing/preprocessing_test.py
rBat/preprocessing/testing/testing_helpers/ma_smoothing.py
rbat-0.1.1.dist-info/licenses/LICENSE
rbat-0.1.1.dist-info/METADATA
rbat-0.1.1.dist-info/WHEEL
rbat-0.1.1.dist-info/top_level.txt
rbat-0.1.1.dist-info/RECORD
