Metadata-Version: 2.4
Name: rBat
Version: 0.1.1
Summary: Toolkit for preprocessing rat time-spatial data and quantifying their (artificially induced) OCD-like behaviour.
Author-email: Brandon Carrasco <brandonc.edu@gmail.com>, Daniel Locke <danielocke03@gmail.com>
Project-URL: Repository, https://github.com/brandonc-edu/rBat
Project-URL: Issues, https://github.com/brandonc-edu/rBat/issues
Keywords: rat,time-spatial,preprocessing,OCD,OCD-like,summary measure
Classifier: Programming Language :: Python :: 3.10
Classifier: Development Status :: 5 - Production/Stable
Classifier: Topic :: Scientific/Engineering :: Information Analysis
Classifier: Intended Audience :: Science/Research
Requires-Python: >=3.10
License-File: LICENSE
Requires-Dist: numpy>=2.1.3
Requires-Dist: shapely>=2.0.6
Requires-Dist: scipy>=1.14.1
Provides-Extra: dev
Requires-Dist: pytest>=8.3.5; extra == "dev"
Requires-Dist: twine>=6.1.0; extra == "dev"
Dynamic: license-file
